odoo/addons/easy_my_coop_api/README.rst
odoo/addons/easy_my_coop_api/__init__.py
odoo/addons/easy_my_coop_api/__manifest__.py
odoo/addons/easy_my_coop_api/controllers/__init__.py
odoo/addons/easy_my_coop_api/controllers/controllers.py
odoo/addons/easy_my_coop_api/demo/demo.xml
odoo/addons/easy_my_coop_api/i18n/easy_my_coop_api.pot
odoo/addons/easy_my_coop_api/models/__init__.py
odoo/addons/easy_my_coop_api/models/auth_api_key.py
odoo/addons/easy_my_coop_api/models/external_id_mixin.py
odoo/addons/easy_my_coop_api/models/subscription_request.py
odoo/addons/easy_my_coop_api/readme/CONTRIBUTORS.rst
odoo/addons/easy_my_coop_api/readme/DESCRIPTION.rst
odoo/addons/easy_my_coop_api/readme/ROADMAP.rst
odoo/addons/easy_my_coop_api/readme/USAGE.rst
odoo/addons/easy_my_coop_api/security/ir_rule.xml
odoo/addons/easy_my_coop_api/services/__init__.py
odoo/addons/easy_my_coop_api/services/abstract_emc_service.py
odoo/addons/easy_my_coop_api/services/account_invoice_service.py
odoo/addons/easy_my_coop_api/services/account_payment_service.py
odoo/addons/easy_my_coop_api/services/ping_service.py
odoo/addons/easy_my_coop_api/services/schemas.py
odoo/addons/easy_my_coop_api/services/subscription_request_service.py
odoo/addons/easy_my_coop_api/static/description/index.html
odoo/addons/easy_my_coop_api/tests/__init__.py
odoo/addons/easy_my_coop_api/tests/common.py
odoo/addons/easy_my_coop_api/tests/test_account_invoice.py
odoo/addons/easy_my_coop_api/tests/test_account_payment.py
odoo/addons/easy_my_coop_api/tests/test_external_id_mixin.py
odoo/addons/easy_my_coop_api/tests/test_ping.py
odoo/addons/easy_my_coop_api/tests/test_registry.py
odoo/addons/easy_my_coop_api/tests/test_subscription_requests.py
odoo/addons/easy_my_coop_api/views/external_id_mixin_views.xml
odoo12_addon_easy_my_coop_api-12.0.0.0.1.99.dev60.dist-info/METADATA
odoo12_addon_easy_my_coop_api-12.0.0.0.1.99.dev60.dist-info/WHEEL
odoo12_addon_easy_my_coop_api-12.0.0.0.1.99.dev60.dist-info/top_level.txt
odoo12_addon_easy_my_coop_api-12.0.0.0.1.99.dev60.dist-info/RECORD
